README.md
setup.py
ts3cli/__init__.py
ts3cli/__main__.py
ts3cli/utils.py
ts3cli.egg-info/PKG-INFO
ts3cli.egg-info/SOURCES.txt
ts3cli.egg-info/dependency_links.txt
ts3cli.egg-info/entry_points.txt
ts3cli.egg-info/requires.txt
ts3cli.egg-info/top_level.txt