Metadata-Version: 1.0
Name: ts3cli
Version: 0.10.0
Summary: CLI for Teamspeak 3's query interface
Home-page: https://github.com/Thor77/TS3CLI
Author: Thor77
Author-email: thor77@thor77.org
License: UNKNOWN
Keywords: ts3 teamspeak teamspeak3 ts3cli cli
Platform: UNKNOWN
